{
    "$schema": "https://schema.management.azure.com/schemas/2015-01-01/deploymentParameters.json#",
    "contentVersion": "1.0.0.0",
    "parameters": {
        "components_identitymanagementservices_name": {
            "value": null
        },
        "vaults_IDMKeyVault_name": {
            "value": null
        },
        "namespaces_identitymanager_name": {
            "value": null
        },
        "storageAccounts_2ndcidentitymanagement_name": {
            "value": null
        },
        "serverfarms_IdentityManagementServicePlan_name": {
            "value": null
        },
        "sites_IdentityManagementServices_name": {
            "value": null
        },
        "AuthorizationRules_RootManageSharedAccessKey_name": {
            "value": null
        },
        "AuthorizationRules_CRMSendListen_name": {
            "value": null
        },
        "topics_distributionlistmemberships_name": {
            "value": null
        },
        "topics_distributionlists_name": {
            "value": null
        },
        "topics_domainimport_name": {
            "value": null
        },
        "topics_groupmemberships_name": {
            "value": null
        },
        "topics_groups_name": {
            "value": null
        },
        "topics_licenseimport_name": {
            "value": null
        },
        "topics_licensemanagement_name": {
            "value": null
        },
        "topics_manager_name": {
            "value": null
        },
        "topics_o365groups_name": {
            "value": null
        },
        "topics_sharedmailboxes_name": {
            "value": null
        },
        "topics_sharedmailboxmemberships_name": {
            "value": null
        },
        "topics_sharepoint_name": {
            "value": null
        },
        "topics_sharepointba_name": {
            "value": null
        },
        "topics_sharepointdiscovery_name": {
            "value": null
        },
        "topics_sharepointrfm_name": {
            "value": null
        },
        "topics_users_name": {
            "value": null
        },
        "topics_usersystems_name": {
            "value": null
        },
        "subscriptions_idm_distributionlistmemberships_name": {
            "value": null
        },
        "subscriptions_idm_distributionlists_name": {
            "value": null
        },
        "subscriptions_idm_domainimports_name": {
            "value": null
        },
        "subscriptions_idm_groupmembership_name": {
            "value": null
        },
        "subscriptions_idm_usergroups_name": {
            "value": null
        },
        "subscriptions_idm_licenseimport_name": {
            "value": null
        },
        "subscriptions_idm_licensemanagement_name": {
            "value": null
        },
        "subscriptions_idm_manager_name": {
            "value": null
        },
        "subscriptions_idm_sharedmailboxes_name": {
            "value": null
        },
        "subscriptions_idm_sharedmailboxmemberships_name": {
            "value": null
        },
        "subscriptions_idm_sharepoint_name": {
            "value": null
        },
        "subscriptions_idm_sharepoint_name_1": {
            "value": null
        },
        "subscriptions_idm_sharepointdiscovery_name": {
            "value": null
        },
        "subscriptions_idm_sharepoint_name_2": {
            "value": null
        },
        "subscriptions_idm_users_name": {
            "value": null
        },
        "subscriptions_idm_usersystems_name": {
            "value": null
        }
    }
}